MANIFEST.in
setup.py
version.txt
myppa/__init__.py
myppa/_version.py
myppa/cli.py
myppa/filters.py
myppa/key.py
myppa/package.py
myppa/utils.py
myppa.egg-info/PKG-INFO
myppa.egg-info/SOURCES.txt
myppa.egg-info/dependency_links.txt
myppa.egg-info/entry_points.txt
myppa.egg-info/requires.txt
myppa.egg-info/top_level.txt
myppa/data/templates/build_deb.sh
myppa/data/templates/jenkins_job.xml