Metadata-Version: 1.0
Name: myppa
Version: 0.3.0
Summary: Manage your own PPA
Home-page: https://github.com/ivochkin/myppa-tool
Author: Stanislav Ivochkin
Author-email: isn@extrn.org
License: MIT
Platform: UNKNOWN
